scroller/__init__.py
scroller/__main__.py
scroller/Generator.py
scroller/ImageModel.py
scroller/ImageProxy.py
scroller/main.py
scroller/ManagedThreadPool.py
scroller/qml/delegates/ListDelegateGif.qml
scroller/qml/delegates/ListDelegateImage.qml
scroller/qml/gui.qml
scroller/qml.qrc
scroller/qml_rc.py
scroller-0.2.1.dist-info/entry_points.txt
scroller-0.2.1.dist-info/LICENSE
scroller-0.2.1.dist-info/METADATA
scroller-0.2.1.dist-info/WHEEL
scroller-0.2.1.dist-info/RECORD
