Metadata-Version: 2.1
Name: scroller
Version: 0.2.1
Summary: 
License: LGPLv2.1
Author: robert-clayton
Author-email: 41345902+robert-clayton@users.noreply.github.com
Requires-Python: >=3.9,<3.12
Classifier: License :: Other/Proprietary License
Classifier: Programming Language :: Python :: 3
Classifier: Programming Language :: Python :: 3.9
Classifier: Programming Language :: Python :: 3.10
Classifier: Programming Language :: Python :: 3.11
Requires-Dist: pillow (>=9.4.0,<10.0.0)
Requires-Dist: pyside6 (>=6.4.2,<7.0.0)
